cscmiko/__init__.py
cscmiko/exceptions.py
cscmiko/helpers.py
cscmiko/devices/__init__.py
cscmiko/devices/base/__init__.py
cscmiko/devices/base/device.py
cscmiko/devices/base/model.py
cscmiko/devices/firewall/__init__.py
cscmiko/devices/routers/__init__.py
cscmiko/devices/switches/__init__.py
cscmiko/devices/switches/base.py
cscmiko/devices/switches/catalyst/__init__.py
cscmiko/devices/switches/catalyst/generic.py
cscmiko/devices/switches/nexus/__init__.py
cscmiko/devices/switches/nexus/generic.py
cscmiko/devices/wlcs/__init__.py
cscmiko/fetch-templates/templates/cisco_ios_show_cdp_neighbors_detail.template
cscmiko/fetch-templates/templates/cisco_ios_show_interfaces.template
cscmiko/fetch-templates/templates/cisco_ios_show_ip_access-lists.template
cscmiko/fetch-templates/templates/cisco_ios_show_ip_bgp.template
cscmiko/fetch-templates/templates/cisco_ios_show_ip_bgp_neighbors.template
cscmiko/fetch-templates/templates/cisco_ios_show_ip_eigrp_neighbors.template
cscmiko/fetch-templates/templates/cisco_ios_show_ip_ospf_neighbor.template
cscmiko/fetch-templates/templates/cisco_ios_show_ip_route.template
cscmiko/fetch-templates/templates/cisco_ios_show_processes_cpu.template
cscmiko/fetch-templates/templates/cisco_ios_show_processes_memory.template
cscmiko/fetch-templates/templates/cisco_ios_show_run_section_interface.template
cscmiko/fetch-templates/templates/cisco_ios_show_spanning-tree.template
cscmiko/fetch-templates/templates/cisco_ios_show_version.template
cscmiko/fetch-templates/templates/cisco_ios_show_vlan.template
cscmiko/fetch-templates/templates/cisco_ios_show_vrf.template
cscmiko/fetch-templates/templates/cisco_ios_show_vtp_status.template
cscmiko/fetch-templates/templates/cisco_nxos_show_access-lists.template
cscmiko/fetch-templates/templates/cisco_nxos_show_cdp_neighbors_detail.template
cscmiko/fetch-templates/templates/cisco_nxos_show_interface.template
cscmiko/fetch-templates/templates/cisco_nxos_show_ip_route.template
cscmiko-0.0.21.dist-info/METADATA
cscmiko-0.0.21.dist-info/RECORD
cscmiko-0.0.21.dist-info/WHEEL
cscmiko-0.0.21.dist-info/top_level.txt
