Metadata-Version: 2.1
Name: cscmiko
Version: 0.0.21
Summary: cisco devices SDK based on netmiko
Home-page: https://github.com/Ali-aqrabawi/cscmiko
Author: ali aqrabawi
Author-email: ali_aqrabawi@yahoo.com
License: UNKNOWN
Platform: UNKNOWN
Classifier: Programming Language :: Python :: 3
Classifier: License :: OSI Approved :: MIT License
Classifier: Operating System :: OS Independent
Requires-Dist: jinja2
Requires-Dist: netmiko
